{
  "name": "컬처피플",
  "url": "https://culturepeople.co.kr",
  "getStartedUrl": "https://culturepeople.co.kr",
  "ogImage": "https://culturepeople.co.kr/og.jpg",
  "shortDescription": "문화를 전하는 사람들",
  "description": "컬처피플은 문화, 연예, 스포츠, 라이프 등 다양한 분야의 뉴스를 신속하고 정확하게 전달하는 종합 인터넷 뉴스 미디어입니다.",
  "links": {
    "twitter": "https://twitter.com/culturepeople",
    "github": "https://github.com/culturepeople",
    "email": "contact@culturepeople.co.kr"
  },
  "pricing": {
    "pro": "https://culturepeople.co.kr",
    "team": "https://culturepeople.co.kr"
  },
  "stats": {
    "figma": 0,
    "github": 0,
    "cli": 0,
    "total": "0",
    "updated": "2024",
    "sections": 0,
    "illustrations": 0,
    "animations": 0,
    "appTemplates": 0,
    "websiteTemplates": 0
  }
}
